twodolib/__init__.py
twodolib/cli.py
twodolib/urlhelper.py
twodolib-0.5.4.dist-info/AUTHORS.rst
twodolib-0.5.4.dist-info/LICENSE
twodolib-0.5.4.dist-info/METADATA
twodolib-0.5.4.dist-info/WHEEL
twodolib-0.5.4.dist-info/entry_points.txt
twodolib-0.5.4.dist-info/top_level.txt
twodolib-0.5.4.dist-info/RECORD
