Metadata-Version: 2.1
Name: twodolib
Version: 0.5.4
Summary: Functions to manage the 2DoApp from the command line.
Home-page: https://github.com/KarstenSchulz/twodolib
Author: Karsten Schulz
Author-email: github@karstenschulz.biz
License: ISCL
Keywords: twodolib tool task2do task-management
Platform: UNKNOWN
Classifier: Development Status :: 4 - Beta
Classifier: Environment :: Console
Classifier: Environment :: MacOS X
Classifier: Intended Audience :: End Users/Desktop
Classifier: License :: OSI Approved :: ISC License (ISCL)
Classifier: Natural Language :: English
Classifier: Operating System :: MacOS :: MacOS X
Classifier: Programming Language :: Python :: 3.5
Classifier: Programming Language :: Python :: 3.6
Classifier: Topic :: Utilities
